{
    "count": 10,
    "start": 1,
    "total": 98,
    "books": [
        {
            "rating": {
                "max": 10,
                "numRaters": 1,
                "average": "0.0",
                "min": 0
            },
            "subtitle": "",
            "author": [
                "Ulmer, Wendy\/ Knorr, Laura (ILT)"
            ],
            "pubdate": "2007-12",
            "tags": [
                {
                    "count": 1,
                    "name": "繪本",
                    "title": "繪本"
                }
            ],
            "origin_title": "",
            "image": "https://img3.doubanio.com\/mpic\/s5564651.jpg",
            "binding": "",
            "translator": [],
            "catalog": "",
            "pages": "",
            "images": {
                "small": "https://img3.doubanio.com\/spic\/s5564651.jpg",
                "large": "https://img3.doubanio.com\/lpic\/s5564651.jpg",
                "medium": "https://img3.doubanio.com\/mpic\/s5564651.jpg"
            },
            "alt": "https:\/\/book.douban.com\/subject\/4371678\/",
            "id": "4371678",
            "publisher": "",
            "isbn10": "1585363197",
            "isbn13": "9781585363193",
            "title": "\"A\" Isn't for Fox",
            "url": "https:\/\/api.douban.com\/v2\/book\/4371678",
            "alt_title": "",
            "author_intro": "",
            "summary": "Experts know that sometimes the best way to teach a child what something is is to teach him what it isn't. Educator Wendy Ulmer applies that principle in her jaunty, out-of-the-box alphabet A isn't for Fox: An Isn't Alphabet. Running through the alphabet, beginning readers are given a letter and then told what the letter topic isn't. A isn't for box; it isn't for fox. A is for ants that crawl over your socks. Laura Knorr's colorful, engaging artwork perfectly captures the wit and whimsy behind the alphabet that isn't what it seems but is so much more",
            "price": "$ 19.15"
        },
        {
            "rating": {
                "max": 10,
                "numRaters": 0,
                "average": "0.0",
                "min": 0
            },
            "subtitle": "",
            "author": [
                "Jane Belk Moncure"
            ],
            "pubdate": "2001-1",
            "tags": [
                {
                    "count": 1,
                    "name": "认知",
                    "title": "认知"
                },
                {
                    "count": 1,
                    "name": "英文",
                    "title": "英文"
                },
                {
                    "count": 1,
                    "name": "图书馆",
                    "title": "图书馆"
                }
            ],
            "origin_title": "",
            "image": "https://img3.doubanio.com\/mpic\/s11286372.jpg",
            "binding": "",
            "translator": [],
            "catalog": "",
            "pages": "29",
            "images": {
                "small": "https://img3.doubanio.com\/spic\/s11286372.jpg",
                "large": "https://img3.doubanio.com\/lpic\/s11286372.jpg",
                "medium": "https://img3.doubanio.com\/mpic\/s11286372.jpg"
            },
            "alt": "https:\/\/book.douban.com\/subject\/3702390\/",
            "id": "3702390",
            "publisher": "",
            "isbn10": "0717265005",
            "isbn13": "9780717265008",
            "title": "My \"a\" book My first steps to reading",
            "url": "https:\/\/api.douban.com\/v2\/book\/3702390",
            "alt_title": "",
            "author_intro": "",
            "summary": "Little a fills his box with things beginning with the letter \"a\" and is treated to a ride by an astronaut.",
            "price": "0.00"
        },
        {
            "rating": {
                "max": 10,
                "numRaters": 1,
                "average": "0.0",
                "min": 0
            },
            "subtitle": "",
            "author": [
                "Etnier, Jennifer L.\/ Alderman, Dominy (ILT)"
            ],
            "pubdate": "2009-12",
            "tags": [
                {
                    "count": 1,
                    "name": "seld",
                    "title": "seld"
                },
                {
                    "count": 1,
                    "name": "improvment",
                    "title": "improvment"
                }
            ],
            "origin_title": "",
            "image": "https://img3.doubanio.com\/mpic\/s4870703.jpg",
            "binding": "",
            "translator": [],
            "catalog": "",
            "pages": "232",
            "images": {
                "small": "https://img3.doubanio.com\/spic\/s4870703.jpg",
                "large": "https://img3.doubanio.com\/lpic\/s4870703.jpg",
                "medium": "https://img3.doubanio.com\/mpic\/s4870703.jpg"
            },
            "alt": "https:\/\/book.douban.com\/subject\/4581079\/",
            "id": "4581079",
            "publisher": "",
            "isbn10": "0807859907",
            "isbn13": "9780807859902",
            "title": "Bring Your \"A\" Game",
            "url": "https:\/\/api.douban.com\/v2\/book\/4581079",
            "alt_title": "",
            "author_intro": "",
            "summary": "Mental training is just as important as physical training when it comes to success in sport. And like physical fitness, mental toughness is something that can be taught and learned. Yet many young athletes have not learned the psychological skills needed to develop their best game. This book was written specifically for young athletes interested in improving their performance and reaching their potential in sport. \"Bring Your aAa Game\"introduces key strategies for mental training, such as goal setting, pre-performance routines, confidence building, and imagery. Each of the seventeen chapters focuses on a single mental skill and offers key points and exercises designed to reinforce the concepts. The book encourages athletes to incorporate these mental skills into their daily lives and practice sessions so that they become second nature during competition. Whether used at home by student athletes or assigned by coaches as part of team development, \"Bring Your aAa Game\" will help young performers develop a plan for success and learn to deal with the challenges of pursuing excellence in sport.",
            "price": "$ 21.47"
        },
        {
            "rating": {
                "max": 10,
                "numRaters": 0,
                "average": "0.0",
                "min": 0
            },
            "subtitle": "",
            "author": [
                "Marian Picton"
            ],
            "pubdate": "",
            "tags": [],
            "origin_title": "",
            "image": "https://img1.doubanio.com\/f\/shire\/5522dd1f5b742d1e1394a17f44d590646b63871d\/pics\/book-default-medium.gif",
            "binding": "",
            "translator": [],
            "catalog": "",
            "pages": "",
            "images": {
                "small": "https://img1.doubanio.com\/f\/shire\/9ec0301cff99c866e9b4f386743f612d594f1836\/pics\/book-default-small.gif",
                "large": "https://img3.doubanio.com\/f\/shire\/5522dd1f5b742d1e1394a17f44d590646b63871d\/pics\/book-default-large.gif",
                "medium": "https://img1.doubanio.com\/f\/shire\/5522dd1f5b742d1e1394a17f44d590646b63871d\/pics\/book-default-medium.gif"
            },
            "alt": "https:\/\/book.douban.com\/subject\/17816122\/",
            "id": "17816122",
            "publisher": "",
            "isbn10": "1853564036",
            "isbn13": "9781853564031",
            "title": "&quot;A&quot; Level English Language and Literature",
            "url": "https:\/\/api.douban.com\/v2\/book\/17816122",
            "alt_title": "",
            "author_intro": "",
            "summary": "",
            "price": ""
        },
        {
            "rating": {
                "max": 10,
                "numRaters": 0,
                "average": "0.0",
                "min": 0
            },
            "subtitle": "",
            "author": [
                "Andrea Rose"
            ],
            "pubdate": "",
            "tags": [],
            "origin_title": "",
            "image": "https://img1.doubanio.com\/f\/shire\/5522dd1f5b742d1e1394a17f44d590646b63871d\/pics\/book-default-medium.gif",
            "binding": "",
            "translator": [],
            "catalog": "",
            "pages": "",
            "images": {
                "small": "https://img1.doubanio.com\/f\/shire\/9ec0301cff99c866e9b4f386743f612d594f1836\/pics\/book-default-small.gif",
                "large": "https://img3.doubanio.com\/f\/shire\/5522dd1f5b742d1e1394a17f44d590646b63871d\/pics\/book-default-large.gif",
                "medium": "https://img1.doubanio.com\/f\/shire\/5522dd1f5b742d1e1394a17f44d590646b63871d\/pics\/book-default-medium.gif"
            },
            "alt": "https:\/\/book.douban.com\/subject\/17818780\/",
            "id": "17818780",
            "publisher": "",
            "isbn10": "1854440241",
            "isbn13": "9781854440242",
            "title": "&quot;&quot;The Germ&quot;",
            "url": "https:\/\/api.douban.com\/v2\/book\/17818780",
            "alt_title": "",
            "author_intro": "",
            "summary": "",
            "price": ""
        },
        {
            "rating": {
                "max": 10,
                "numRaters": 0,
                "average": "0.0",
                "min": 0
            },
            "subtitle": "",
            "author": [
                "Dimsdale, Thomas"
            ],
            "pubdate": "",
            "tags": [],
            "origin_title": "",
            "image": "https://img3.doubanio.com\/mpic\/s6723465.jpg",
            "binding": "",
            "translator": [],
            "catalog": "",
            "pages": "150",
            "images": {
                "small": "https://img3.doubanio.com\/spic\/s6723465.jpg",
                "large": "https://img3.doubanio.com\/lpic\/s6723465.jpg",
                "medium": "https://img3.doubanio.com\/mpic\/s6723465.jpg"
            },
            "alt": "https:\/\/book.douban.com\/subject\/6661267\/",
            "id": "6661267",
            "publisher": "",
            "isbn10": "1171005865",
            "isbn13": "9781171005865",
            "title": "Observations on the Introduction to the Plan of the Dispensary for General Inoculation with Remarks on a Pamphlet, Entitled, \"\"An Examination of a Cha",
            "url": "https:\/\/api.douban.com\/v2\/book\/6661267",
            "alt_title": "",
            "author_intro": "",
            "summary": "",
            "price": "$ 24.58"
        },
        {
            "rating": {
                "max": 10,
                "numRaters": 0,
                "average": "0.0",
                "min": 0
            },
            "subtitle": "",
            "author": [
                "Multiple Contributors"
            ],
            "pubdate": "2010-9",
            "tags": [],
            "origin_title": "",
            "image": "https://img1.doubanio.com\/mpic\/s10448409.jpg",
            "binding": "",
            "translator": [],
            "catalog": "",
            "pages": "70",
            "images": {
                "small": "https://img1.doubanio.com\/spic\/s10448409.jpg",
                "large": "https://img1.doubanio.com\/lpic\/s10448409.jpg",
                "medium": "https://img1.doubanio.com\/mpic\/s10448409.jpg"
            },
            "alt": "https:\/\/book.douban.com\/subject\/10836542\/",
            "id": "10836542",
            "publisher": "",
            "isbn10": "0699108322",
            "isbn13": "9780699108324",
            "title": "An Abstract of Some Important Parts of a Bill, Now Depending in Parliament, Intituled, \"\"A Bill for the Better Support and Maintenance of the Poor.\"\" Prepared by a Committee of the Joint Vestry of the United Parishes",
            "url": "https:\/\/api.douban.com\/v2\/book\/10836542",
            "alt_title": "",
            "author_intro": "",
            "summary": "",
            "price": "$ 20.06"
        },
        {
            "rating": {
                "max": 10,
                "numRaters": 0,
                "average": "0.0",
                "min": 0
            },
            "subtitle": "",
            "author": [
                "Multiple Contributors"
            ],
            "pubdate": "2010-9",
            "tags": [],
            "origin_title": "",
            "image": "https://img3.doubanio.com\/mpic\/s10448435.jpg",
            "binding": "",
            "translator": [],
            "catalog": "",
            "pages": "66",
            "images": {
                "small": "https://img3.doubanio.com\/spic\/s10448435.jpg",
                "large": "https://img3.doubanio.com\/lpic\/s10448435.jpg",
                "medium": "https://img3.doubanio.com\/mpic\/s10448435.jpg"
            },
            "alt": "https:\/\/book.douban.com\/subject\/10836572\/",
            "id": "10836572",
            "publisher": "",
            "isbn10": "0699110416",
            "isbn13": "9780699110419",
            "title": "History of the Four Last Elections for the County of Suffolk to Which Is Added a PostScript, Relative to MR Sawbridge's Intended Motion \"\"For Shortening the Duration of Parliaments",
            "url": "https:\/\/api.douban.com\/v2\/book\/10836572",
            "alt_title": "",
            "author_intro": "",
            "summary": "",
            "price": "$ 20.06"
        },
        {
            "rating": {
                "max": 10,
                "numRaters": 0,
                "average": "0.0",
                "min": 0
            },
            "subtitle": "",
            "author": [
                "Multiple Contributors"
            ],
            "pubdate": "2010-9",
            "tags": [],
            "origin_title": "",
            "image": "https://img1.doubanio.com\/mpic\/s10448528.jpg",
            "binding": "",
            "translator": [],
            "catalog": "",
            "pages": "46",
            "images": {
                "small": "https://img1.doubanio.com\/spic\/s10448528.jpg",
                "large": "https://img1.doubanio.com\/lpic\/s10448528.jpg",
                "medium": "https://img1.doubanio.com\/mpic\/s10448528.jpg"
            },
            "alt": "https:\/\/book.douban.com\/subject\/10836663\/",
            "id": "10836663",
            "publisher": "",
            "isbn10": "0699117852",
            "isbn13": "9780699117852",
            "title": "A Short State of the Proceedings in the House of Commons, in the Year 1765, on the Petition of the Duke and Duchess of Atholl, Against the Bill, \"\"For the More Effectual Preventing the Mischiefs ... Isle of Man.\"\"",
            "url": "https:\/\/api.douban.com\/v2\/book\/10836663",
            "alt_title": "",
            "author_intro": "",
            "summary": "",
            "price": "$ 17.80"
        },
        {
            "rating": {
                "max": 10,
                "numRaters": 0,
                "average": "0.0",
                "min": 0
            },
            "subtitle": "",
            "author": [
                "Multiple Contributors"
            ],
            "pubdate": "2010-9",
            "tags": [],
            "origin_title": "",
            "image": "https://img3.doubanio.com\/mpic\/s10448724.jpg",
            "binding": "",
            "translator": [],
            "catalog": "",
            "pages": "26",
            "images": {
                "small": "https://img3.doubanio.com\/spic\/s10448724.jpg",
                "large": "https://img3.doubanio.com\/lpic\/s10448724.jpg",
                "medium": "https://img3.doubanio.com\/mpic\/s10448724.jpg"
            },
            "alt": "https:\/\/book.douban.com\/subject\/10836855\/",
            "id": "10836855",
            "publisher": "",
            "isbn10": "0699132916",
            "isbn13": "9780699132916",
            "title": "Uggeshall Inclosure. a State of the Claims, Delivered to the Commissioners Named and Authorised, in and by an Act of Parliament Entitled \"\"An ACT for Dividing and Inclosing the Heaths",
            "url": "https:\/\/api.douban.com\/v2\/book\/10836855",
            "alt_title": "",
            "author_intro": "",
            "summary": "",
            "price": "$ 16.67"
        }
    ]
}